xai_sdk/__about__.py
xai_sdk/__init__.py
xai_sdk/auth.py
xai_sdk/chat.py
xai_sdk/client.py
xai_sdk/collections.py
xai_sdk/image.py
xai_sdk/meta.py
xai_sdk/models.py
xai_sdk/search.py
xai_sdk/tokenizer.py
xai_sdk/tools.py
xai_sdk/aio/__init__.py
xai_sdk/aio/auth.py
xai_sdk/aio/chat.py
xai_sdk/aio/client.py
xai_sdk/aio/collections.py
xai_sdk/aio/image.py
xai_sdk/aio/models.py
xai_sdk/aio/tokenizer.py
xai_sdk/proto/__init__.py
xai_sdk/proto/v5/auth_pb2.py
xai_sdk/proto/v5/auth_pb2.pyi
xai_sdk/proto/v5/auth_pb2_grpc.py
xai_sdk/proto/v5/chat_pb2.py
xai_sdk/proto/v5/chat_pb2.pyi
xai_sdk/proto/v5/chat_pb2_grpc.py
xai_sdk/proto/v5/collections_pb2.py
xai_sdk/proto/v5/collections_pb2.pyi
xai_sdk/proto/v5/collections_pb2_grpc.py
xai_sdk/proto/v5/deferred_pb2.py
xai_sdk/proto/v5/deferred_pb2.pyi
xai_sdk/proto/v5/deferred_pb2_grpc.py
xai_sdk/proto/v5/documents_pb2.py
xai_sdk/proto/v5/documents_pb2.pyi
xai_sdk/proto/v5/documents_pb2_grpc.py
xai_sdk/proto/v5/embed_pb2.py
xai_sdk/proto/v5/embed_pb2.pyi
xai_sdk/proto/v5/embed_pb2_grpc.py
xai_sdk/proto/v5/image_pb2.py
xai_sdk/proto/v5/image_pb2.pyi
xai_sdk/proto/v5/image_pb2_grpc.py
xai_sdk/proto/v5/models_pb2.py
xai_sdk/proto/v5/models_pb2.pyi
xai_sdk/proto/v5/models_pb2_grpc.py
xai_sdk/proto/v5/sample_pb2.py
xai_sdk/proto/v5/sample_pb2.pyi
xai_sdk/proto/v5/sample_pb2_grpc.py
xai_sdk/proto/v5/shared_pb2.py
xai_sdk/proto/v5/shared_pb2.pyi
xai_sdk/proto/v5/shared_pb2_grpc.py
xai_sdk/proto/v5/tokenize_pb2.py
xai_sdk/proto/v5/tokenize_pb2.pyi
xai_sdk/proto/v5/tokenize_pb2_grpc.py
xai_sdk/proto/v5/types_pb2.py
xai_sdk/proto/v5/types_pb2.pyi
xai_sdk/proto/v5/types_pb2_grpc.py
xai_sdk/proto/v5/usage_pb2.py
xai_sdk/proto/v5/usage_pb2.pyi
xai_sdk/proto/v5/usage_pb2_grpc.py
xai_sdk/proto/v6/auth_pb2.py
xai_sdk/proto/v6/auth_pb2.pyi
xai_sdk/proto/v6/auth_pb2_grpc.py
xai_sdk/proto/v6/chat_pb2.py
xai_sdk/proto/v6/chat_pb2.pyi
xai_sdk/proto/v6/chat_pb2_grpc.py
xai_sdk/proto/v6/collections_pb2.py
xai_sdk/proto/v6/collections_pb2.pyi
xai_sdk-1.3.1.dist-info/METADATA
xai_sdk-1.3.1.dist-info/WHEEL
xai_sdk-1.3.1.dist-info/licenses/LICENSE
xai_sdk-1.3.1.dist-info/RECORD
