Metadata-Version: 2.4
Name: xai-sdk
Version: 1.3.1
Summary: The official Python SDK for the xAI API
Project-URL: Homepage, https://github.com/xai-org/xai-sdk-python
Project-URL: Documentation, https://docs.x.ai
Project-URL: Repository, https://github.com/xai-org/xai-sdk-python
Author-email: xAI <support@x.ai>
License-Expression: Apache-2.0
License-File: LICENSE
Classifier: Development Status :: 5 - Production/Stable
Classifier: Environment :: Web Environment
Classifier: Intended Audience :: Developers
Classifier: Intended Audience :: Science/Research
Classifier: License :: OSI Approved :: Apache Software License
Classifier: Operating System :: MacOS :: MacOS X
Classifier: Operating System :: Microsoft :: Windows
Classifier: Operating System :: POSIX :: Linux
Classifier: Programming Language :: Python
Classifier: Programming Language :: Python :: 3.10
Classifier: Programming Language :: Python :: 3.11
Classifier: Programming Language :: Python :: 3.12
Classifier: Programming Language :: Python :: 3.13
Classifier: Programming Language :: Python :: Implementation :: CPython
Classifier: Programming Language :: Python :: Implementation :: PyPy
Classifier: Topic :: Internet :: WWW/HTTP
Classifier: Topic :: Scientific/Engineering :: Artificial Intelligence
Classifier: Topic :: Software Development :: Libraries
Classifier: Topic :: Software Development :: Libraries :: Python Modules
Classifier: Typing :: Typed
Requires-Python: >=3.10
Requires-Dist: aiohttp<4,>=3.8.6
Requires-Dist: grpcio<2,>=1.72.1
Requires-Dist: opentelemetry-sdk<2,>=1.36.0
Requires-Dist: packaging<26,>=25.0
Requires-Dist: protobuf<7,>=5.29.4
Requires-Dist: pydantic<3,>=2.5.3
Requires-Dist: requests<3,>=2.31.0
Provides-Extra: telemetry-grpc
Requires-Dist: opentelemetry-exporter-otlp-proto-grpc<2,>=1.36.0; extra == 'telemetry-grpc'
Provides-Extra: telemetry-http
Requires-Dist: opentelemetry-exporter-otlp-proto-http<2,>=1.36.0; extra == 'telemetry-http'
